{
  "headers": {
    "content-length": "708",
    "x-amz-request-id": "Z7TGZMAYX0F8EPKV",
    "cache-control": "public, max-age=31536000, immutable",
    "date": "Sun, 11 Jul 2021 19:37:47 GMT",
    "x-amz-id-2": "tLy9etqrLXTMfYYBQ/QlMaMQuxE1xvrR1kDRol7V5DYIyNE6GWcCM2+mA6qaQHOl5ardabOHVj8=",
    "server": "cloudflare",
    "expect-ct": "max-age=604800, report-uri=\"https://report-uri.cloudflare.com/cdn-cgi/beacon/expect-ct\"",
    "via": "HTTP/1.1 deploy",
    "cf-cache-status": "DYNAMIC",
    "etag": "\"b5ac166d3158179ee451ecb99b4c2520\"",
    "last-modified": "Tue, 29 Jun 2021 15:47:22 GMT",
    "content-type": "application/typescript; charset=utf-8",
    "alt-svc": "h3-27=\":443\"; ma=86400, h3-28=\":443\"; ma=86400, h3-29=\":443\"; ma=86400, h3=\":443\"; ma=86400",
    "x-deno-ray": "us-central1-b::e19319349bc5e7d0e40b9e098eceefd9",
    "cf-ray": "66d47d08acdf2a66-ORD",
    "access-control-allow-origin": "*",
    "vary": "Accept-Encoding",
    "x-amz-version-id": "0jHMTqJwgmXxA1iY5Qadf4Urv41wFZO0"
  },
  "url": "https://deno.land/std@0.100.0/fs/exists.ts"
}